eth_tester_rpc/__init__.py
eth_tester_rpc/cli.py
eth_tester_rpc/formatter.py
eth_tester_rpc/pyevm_backend.py
eth_tester_rpc/rpc.py
eth_tester_rpc/server.py
eth_tester_rpc/tester.py
eth_tester_rpc/utils/__init__.py
eth_tester_rpc/utils/abi.py
eth_tester_rpc/utils/conversion.py
eth_tester_rpc/utils/decorators.py
eth_tester_rpc/utils/encoding.py
eth_tester_rpc/utils/formatters.py
eth_tester_rpc/utils/solidity.py
eth_tester_rpc/utils/validation.py
eth_tester_rpc/utils/compat_threading/__init__.py
eth_tester_rpc/utils/compat_threading/compat_gevent.py
eth_tester_rpc/utils/compat_threading/compat_stdlib.py
eth_tester_rpc/utils/toolz/__init__.py
eth_tester_rpc/utils/toolz/curried.py
eth_tester_rpc-0.5.0b1.dist-info/LICENSE
eth_tester_rpc-0.5.0b1.dist-info/METADATA
eth_tester_rpc-0.5.0b1.dist-info/WHEEL
eth_tester_rpc-0.5.0b1.dist-info/entry_points.txt
eth_tester_rpc-0.5.0b1.dist-info/top_level.txt
eth_tester_rpc-0.5.0b1.dist-info/RECORD
