Metadata-Version: 2.1
Name: eth-tester-rpc
Version: 0.5.0b1
Summary: Python TestRPC for ethereum
Home-page: https://github.com/voith/eth-tester-rpc
Author: voith
Author-email: voithjm1@gmail.com
License: MIT
Keywords: ethereum
Platform: UNKNOWN
Classifier: Development Status :: 3 - Alpha
Classifier: Intended Audience :: Developers
Classifier: License :: OSI Approved :: MIT License
Classifier: Natural Language :: English
Classifier: Programming Language :: Python :: 3
Classifier: Programming Language :: Python :: 3.6
Classifier: Programming Language :: Python :: 3.7
Requires-Python: >=3.6, <4
Requires-Dist: eth-utils (<2,>=1)
Requires-Dist: eth-tester[py-evm] (==0.5.0b3)
Requires-Dist: json-rpc (>=1.10.3)
Requires-Dist: Werkzeug (>=0.11.10)
Requires-Dist: click (>=6.6)
Requires-Dist: cytoolz (<1.0.0,>=0.9.0) ; implementation_name == "cpython"
Requires-Dist: eth-hash[pysha3] (<1.0.0,>=0.1.4) ; implementation_name == "cpython"
Requires-Dist: toolz (<1.0.0,>=0.9.0) ; implementation_name == "pypy"
Requires-Dist: eth-hash[pycryptodome] (<1.0.0,>=0.1.4) ; implementation_name == "pypy"
Provides-Extra: dev
Requires-Dist: bumpversion (<1,>=0.5.3) ; extra == 'dev'
Requires-Dist: pytest-watch (<5,>=4.1.0) ; extra == 'dev'
Requires-Dist: wheel ; extra == 'dev'
Requires-Dist: twine ; extra == 'dev'
Requires-Dist: ipython ; extra == 'dev'
Requires-Dist: pytest (>=4.4.0) ; extra == 'dev'
Requires-Dist: pytest-xdist ; extra == 'dev'
Requires-Dist: tox (<3,>=2.9.1) ; extra == 'dev'
Requires-Dist: requests (<3.0.0,>=2.16.0) ; extra == 'dev'
Requires-Dist: eth-account (<0.6.0,>=0.5.3) ; extra == 'dev'
Requires-Dist: eth-abi (<3.0.0,>=2.0.0b4) ; extra == 'dev'
Requires-Dist: web3 (<6.0.0,>=5.0.0b2) ; extra == 'dev'
Requires-Dist: splinter (<1.0.0,>=0.10.0) ; extra == 'dev'
Requires-Dist: flake8 (==3.4.1) ; extra == 'dev'
Requires-Dist: isort (<5,>=4.2.15) ; extra == 'dev'
Requires-Dist: Sphinx (<2,>=1.6.5) ; extra == 'dev'
Requires-Dist: sphinx-rtd-theme (>=0.1.9) ; extra == 'dev'
Provides-Extra: doc
Requires-Dist: Sphinx (<2,>=1.6.5) ; extra == 'doc'
Requires-Dist: sphinx-rtd-theme (>=0.1.9) ; extra == 'doc'
Provides-Extra: gevent
Requires-Dist: gevent (<1.2.0,>=1.1.1) ; extra == 'gevent'
Provides-Extra: lint
Requires-Dist: flake8 (==3.4.1) ; extra == 'lint'
Requires-Dist: isort (<5,>=4.2.15) ; extra == 'lint'
Provides-Extra: test
Requires-Dist: pytest (>=4.4.0) ; extra == 'test'
Requires-Dist: pytest-xdist ; extra == 'test'
Requires-Dist: tox (<3,>=2.9.1) ; extra == 'test'
Requires-Dist: requests (<3.0.0,>=2.16.0) ; extra == 'test'
Requires-Dist: eth-account (<0.6.0,>=0.5.3) ; extra == 'test'
Requires-Dist: eth-abi (<3.0.0,>=2.0.0b4) ; extra == 'test'
Requires-Dist: web3 (<6.0.0,>=5.0.0b2) ; extra == 'test'
Requires-Dist: splinter (<1.0.0,>=0.10.0) ; extra == 'test'
